streaminghub_proxy_pupil_core/__init__.py
streaminghub_proxy_pupil_core/node.json
streaminghub_proxy_pupil_core/proxy.py
streaminghub_proxy_pupil_core/test.py
streaminghub_proxy_pupil_core-0.0.1.dist-info/METADATA
streaminghub_proxy_pupil_core-0.0.1.dist-info/WHEEL
streaminghub_proxy_pupil_core-0.0.1.dist-info/entry_points.txt
streaminghub_proxy_pupil_core-0.0.1.dist-info/top_level.txt
streaminghub_proxy_pupil_core-0.0.1.dist-info/RECORD
